[{"importDeclarations":[{"moduleName":"@storybook/html","bindings":["storiesOf"]},{"moduleName":"./../src/components/11-atoms/badge/badge.html","bindings":["Badge"]},{"moduleName":"./../src/css/freeform.css","bindings":[]},{"moduleName":"./../src/css/styles.css","bindings":[]}],"stories":[{"externalComponentId":"5e30daa01c35b8111d412e39","kind":"Components|Atoms/Badge","name":"Badge","dsmInfo":{"id":"5e30daa01c35b8111d412e39","docgenInfo":null},"frameworkMetadata":null}]},{"importDeclarations":[{"moduleName":"@storybook/html","bindings":["storiesOf"]},{"moduleName":"./../src/components/00-atoms/button/button.html","bindings":["Button"]},{"moduleName":"./../src/css/freeform.css","bindings":[]},{"moduleName":"./../src/css/styles.css","bindings":[]}],"stories":[{"externalComponentId":"5e30dac870092c6c05aa0860","kind":"Components|Atoms/Buttons","name":"Button","dsmInfo":{"id":"5e30dac870092c6c05aa0860","docgenInfo":null},"frameworkMetadata":null}]}]
